programs/__init__.py
programs/ant_colony_algorithm.py
programs/genetic_algorithm.py
programs/gray_wolf_optimization.py
programs/particle_swarn_optimization.py
programs/shuffuled_frog_optimization.py
programs/simulated_annealing.py
programs/tabu_search.py
programs/travel_salesman_problem.py
utils/__init__.py
utils/plot_graph.py
optimization_techniques-1.5.dist-info/LICENSE
optimization_techniques-1.5.dist-info/METADATA
optimization_techniques-1.5.dist-info/WHEEL
optimization_techniques-1.5.dist-info/top_level.txt
optimization_techniques-1.5.dist-info/RECORD
