Metadata-Version: 2.1
Name: optimization_techniques
Version: 1.5
Summary: Some Optimization Problems for Machine Learning
Home-page: https://github.com/KeerthiVasan-ai/optimization-techniques
Author: Keerthivasan S
Author-email: keerthi77459@gmail.com
Classifier: Programming Language :: Python :: 3
Classifier: License :: OSI Approved :: MIT License
Classifier: Operating System :: OS Independent
License-File: LICENSE
